bert_service/__init__.py
bert_service/batching.py
bert_service/bert_service.py
bert_service/nlp_reader.py
bert_service/tokenization.py
bert_service/vocab/cased_vocab.txt
bert_service/vocab/chinese_vocab.txt
bert_service/vocab/multi_cased_vocab.txt
bert_service/vocab/uncased_vocab.txt
bert_service-0.3.7.dist-info/LICENSE
bert_service-0.3.7.dist-info/METADATA
bert_service-0.3.7.dist-info/WHEEL
bert_service-0.3.7.dist-info/top_level.txt
bert_service-0.3.7.dist-info/RECORD
